MANIFEST.in
README.rst
requirements.txt
setup.cfg
setup.py
djmicrosip_auditacotizacion/__init__.py
djmicrosip_auditacotizacion/__init__.pyc
djmicrosip_auditacotizacion/config.pyc
djmicrosip_auditacotizacion/forms.pyc
djmicrosip_auditacotizacion/models.pyc
djmicrosip_auditacotizacion/urls.pyc
djmicrosip_auditacotizacion/views.pyc
djmicrosip_auditacotizacion.egg-info/PKG-INFO
djmicrosip_auditacotizacion.egg-info/SOURCES.txt
djmicrosip_auditacotizacion.egg-info/dependency_links.txt
djmicrosip_auditacotizacion.egg-info/requires.txt
djmicrosip_auditacotizacion.egg-info/top_level.txt
djmicrosip_auditacotizacion/static/djmicrosip_auditacotizacion/audio/beep.wav
djmicrosip_auditacotizacion/static/djmicrosip_auditacotizacion/js/auditoria.js
djmicrosip_auditacotizacion/templates/djmicrosip_auditacotizacion/auditoria.html
djmicrosip_auditacotizacion/templates/djmicrosip_auditacotizacion/base.html
djmicrosip_auditacotizacion/templates/djmicrosip_auditacotizacion/index.html